setup.py
requests_plus/__init__.py
requests_plus.egg-info/PKG-INFO
requests_plus.egg-info/SOURCES.txt
requests_plus.egg-info/dependency_links.txt
requests_plus.egg-info/top_level.txt