Metadata-Version: 1.0
Name: requests-plus
Version: 0.0.1
Summary: Requests's plus version.
Home-page: UNKNOWN
Author: CK(Yanwentao)
Author-email: 3504802487@qq.com
License: UNKNOWN
Platform: UNKNOWN
